grayhacker/__init__.py
grayhacker/webdriver_setup.py
grayhacker-0.1.0.dist-info/METADATA
grayhacker-0.1.0.dist-info/WHEEL
grayhacker-0.1.0.dist-info/top_level.txt
grayhacker-0.1.0.dist-info/RECORD
