Metadata-Version: 2.1
Name: grayhacker
Version: 0.1.0
Summary: A library for automating Selenium WebDriver setup
Author: Your Name
Author-email: your_email@example.com
Classifier: Programming Language :: Python :: 3
Classifier: License :: OSI Approved :: MIT License
Classifier: Operating System :: OS Independent
Requires-Dist: selenium
